textual_slidecontainer/__init__.py
textual_slidecontainer/demo.py
textual_slidecontainer/demostyles.tcss
textual_slidecontainer/py.typed
textual_slidecontainer/slidecontainer.py
textual_slidecontainer-1.0.0.dist-info/METADATA
textual_slidecontainer-1.0.0.dist-info/WHEEL
textual_slidecontainer-1.0.0.dist-info/entry_points.txt
textual_slidecontainer-1.0.0.dist-info/RECORD
