Metadata-Version: 2.4
Name: textual-slidecontainer
Version: 1.0.0
Summary: A Sliding Container widget for Textual
Project-URL: Repository, https://github.com/edward-jazzhands/textual-slidecontainer
Project-URL: Changelog, https://github.com/edward-jazzhands/textual-slidecontainer/blob/master/CHANGELOG.md
Author-email: edward-jazzhands <ed.jazzhands@gmail.com>
License: MIT
Keywords: python,slidecontainer,textual,tui,widget
Classifier: Development Status :: 5 - Production/Stable
Classifier: License :: OSI Approved :: MIT License
Classifier: Operating System :: OS Independent
Classifier: Programming Language :: Python
Classifier: Programming Language :: Python :: 3 :: Only
Classifier: Programming Language :: Python :: 3.9
Classifier: Programming Language :: Python :: 3.10
Classifier: Programming Language :: Python :: 3.11
Classifier: Programming Language :: Python :: 3.12
Classifier: Programming Language :: Python :: 3.13
Requires-Python: >=3.9
Requires-Dist: textual<6.0.0,>=3.0.0
